Workbook

Sheet Compras
A1: LISTA DE COMPRAS — PROJETO ROBÔ DA LARA · v4.2
A2: Preços verificados a 18/08/2026 em lojas PT e DE, com IVA; reSpeaker e coluna revistos a 25/08/2026. Confirmar sempre antes de encomendar.
A4: Encomenda | B4: Fase | C4: Peça | D4: Para que serve / porquê | E4: Qtd | F4: Preço un. | G4: Total | H4: Fornecedor | I4: Preço confirmado? | J4: Notas importantes
A5: 1 · Cérebro e voz | B5: 1 | C5: Raspberry Pi 5 · 4 GB | D5: O computador do robô. Corre visão, voz e controlo. | E5: 1 | F5: 95.9 | G5: =E5*F5 -> 95.9 | H5: Botnroll (PT) | I5: Sim | J5: PTRobotics vende o MESMO por €131,98 — comparar sempre. Preços subiram 2x em 2026 pela escassez mundial de LPDDR4X. Upgrade 8GB: +€93 (só se quiserem correr também um LLM local).
A6: 1 · Cérebro e voz | B6: 1 | C6: Fonte oficial USB-C 27 W | D6: Alimentação de bancada, para as fases 1-4. | E6: 1 | F6: 13.9 | G6: =E6*F6 -> 13.9 | H6: Botnroll (PT) | I6: Sim | J6: A partir da fase 5 o robô passa a usar a bateria. Esta fica para a bancada.
A7: 1 · Cérebro e voz | B7: 1 | C7: Cartão microSD 64 GB A2/V30 | D7: Onde vive o sistema operativo e o código. | E7: 1 | F7: 14 | G7: =E7*F7 -> 14 | H7: Qualquer | I7: Estimativa | J7: Tem de ser A2 — os cartões lentos tornam o Pi insuportável.
A8: 1 · Cérebro e voz | B8: 1 | C8: Active Cooler oficial (ventoinha) | D8: O Pi 5 aquece e reduz a velocidade sem arrefecimento. | E8: 1 | F8: 5.5 | G8: =E8*F8 -> 5.5 | H8: Botnroll (PT) | I8: Estimativa | J8: Não é opcional se o robô vai correr Whisper e OpenCV.
A9: 1 · Cérebro e voz | B9: 1 | C9: Jumpers, breadboard, parafusos M2.5/M3 | D9: Consumíveis. Comprar a dobrar — perdem-se sempre. | E9: 1 | F9: 17 | G9: =E9*F9 -> 17 | H9: Qualquer | I9: Estimativa | J9: Jumper M-F, M-M e F-F. Parafusos M2.5 para o Pi e M3 para a estrutura.
A10: 1 · Cérebro e voz | B10: 2 | C10: reSpeaker XVF3800 USB — 4 mics com AEC, E A PLACA DE SOM | D10: OS OUVIDOS E A VOZ. A coluna liga-se a ele, não ao Pi (o Pi 5 não tem saída de som). | E10: 1 | F10: 60 | G10: =E10*F10 -> 60 | H10: Gotronic (FR) / Botland (PL) | I10: Sim | J10: ⚠️ VEM JÁ NA ENCOMENDA 1 PORQUE É POR ELE QUE SAI O SOM. Em modo USB o XMOS só cancela o eco se for o Pi a mandar-lhe o áudio por USB — é esse fluxo que serve de referência ao AEC. Um amplificador I2S no Pi (a escolha anterior, MAX98357A) tocava ao lado dele e deixava-o sem referência. A placa tem saída de coluna amplificada em JST PH 2.0 (até 5 W) e jack 3,5 mm. Zero soldadura, zero drivers (UAC 2.0), nada no config.txt — só duas linhas em /etc/asound.conf. ⚠️ NÃO EXISTE EM LOJA PT e o stock europeu anda apertado (Gotronic €59,90 com reposições; Kiwi esgotada; Seeed direta $60,99): encomendar no mesmo dia que o resto. Plano B: reSpeaker Lite €25 (tem AEC e saída de coluna, não tem beamforming).
A11: 1 · Cérebro e voz | B11: 2 | C11: Coluna DFRobot 3 W · 8 Ω · ficha JST PH 2.0 (Botnroll: 'Coluna stereo - 3W') | D11: Onde sai o som. Encaixa diretamente na ficha JST PH 2.0 do reSpeaker. | E11: 1 | F11: 4.95 | G11: =E11*F11 -> 4.95 | H11: Botnroll (PT) | I11: Sim | J11: Apesar do nome na loja, é UMA coluna (DFRobot, ref. ELT03006): 3 W, 8 Ω, caixa fechada 70×30×16 mm, cabo de 42 cm já com ficha JST PH 2.0 — a mesma da saída do reSpeaker. Em stock a 25/08/2026. 8 Ω é o certo para o amplificador da placa; testar o sítio antes de colar — a caixa fechada dá mais grave que um cone nu.
A12: 1 · Cérebro e voz | B12: 9 | C12: Camera Module 3 · 76° · 12 MP (oficial, SC1223) | D12: Os olhos que veem. Autofoco — decisivo para caras a 1-3 m. | E12: 1 | F12: 32.8 | G12: =E12*F12 -> 32.8 | H12: Botnroll (PT) | I12: Sim | J12: Só é precisa na fase 9, mas vem já: mesma loja que o Pi, poupa um envio. MAIS BARATA NA MAUSER: €29,99 com 80 unidades em stock e levantamento grátis nas lojas (Porto, Lisboa, Leiria, Corroios, Portela, Freixeira, Funchal). Poupa €2,81 — só compensa se fores lá levantar ou se juntares mais de €50.
A13: 1 · Cérebro e voz | B13: 9 | C13: Cabo CSI oficial 22→15 pinos · 200 mm (SC1128) | D13: Sem isto a câmara NÃO liga ao Pi 5. | E13: 1 | F13: 1.2 | G13: =E13*F13 -> 1.2 | H13: Botnroll (PT) | I13: Sim | J13: ⚠️ ERRO MAIS COMUM DO PI 5. O Pi 5 mudou para conectores de 22 pinos; a câmara vem com o cabo antigo de 15. É o cabo OFICIAL da Raspberry Pi, ref. CAB07019 na Botnroll. Na Mauser é o SC1892 a €1,17.
A14: 2 · A cara e a energia | B14: 3 | C14: Painel HUB75 64×32 RGB (P2.5) — A CARA | D14: 16 milhões de cores, 2048 pixéis. O coração pode ser vermelho. | E14: 1 | F14: 20 | G14: =E14*F14 -> 20 | H14: The Pi Hut (UK) | I14: Sim | J14: £17,30 no Pi Hut, em stock. ⚠️ Mede 160×80 mm — a cabeça tem de crescer de ~16 para ~18 cm. 64×32 é EXATAMENTE o máximo dos sliders do bot-face. Consumo real 0,3-0,6 A (os 4 A anunciados são branco total). Alimentar do barramento de 5,1 V com fio grosso e fusível PRÓPRIO, nunca pelo ESP32.
A15: 2 · A cara e a energia | B15: 3 | C15: Cablagem HUB75 ↔ ESP32 (shield ou protoboard) | D15: 13 fios entre o painel e o ESP32. | E15: 1 | F15: 12 | G15: =E15*F15 -> 12 | H15: Qualquer | I15: Estimativa | J15: O ESP32 Trinity e o MatrixPortal S3 estavam esgotados em 2026 — fazer à mão numa protoboard, ou procurar um ESP32 I2S Matrix Shield. O ESP32 em si é o que já temos: custo zero.
A16: 2 · A cara e a energia | B16: 5 | C16: Pack LiFePO4 4S 12,8 V ~6 Ah com BMS | D16: A bateria única de todo o sistema. ~77 Wh = 4h+. | E16: 1 | F16: 60 | G16: =E16*F16 -> 60 | H16: eBay.de / Amazon.de | I16: Estimativa | J16: ⚠️ QUÍMICA ESCOLHIDA POR SEGURANÇA: a LFP não tem fuga térmica auto-alimentada como a Li-ion/LiPo. Stock escasso em lojas maker PT — confirmar cedo. Plano B: 3S Li-ion 18650 com BMS em caixa rígida. ⚠️ PEDIR BMS DE PORTA COMUM (common port): o robô fica ligado à ficha em cima da secretária, e um BMS de porta separada não deixa carregar e descarregar ao mesmo tempo.
... A43: 5 · Sobressalentes | B43: — | C43: 1× MG90S, 1× TB6612, fusíveis e cabos extra | D43: Coisas partem-se num projeto de 4 meses. | E43: 1 | F43: 25 | G43: =E43*F43 -> 25 | H43: Qualquer | I43: Estimativa | J43: Esperar uma semana por uma peça de €5 mata o ritmo — e o entusiasmo de uma criança de 11 anos.
C45: TOTAL BASE | G45: =SUM(G5:G43) -> 882.05 | H45: Orçamento definido: até €1000

Sheet Resumo
A1: RESUMO DO ORÇAMENTO · v4.2
A3: Encomenda | B3: Quando comprar | C3: Nº de peças | D3: Custo
A4: 1 · Cérebro e voz | B4: Agora — precisa nas fases 1-3 (o reSpeaker é a placa de som: fase 2) | C4: =COUNTIF(Compras!$A$5:$A$44,A4) -> 9 | D4: =SUMIF(Compras!$A$5:$A$44,A4,Compras!$G$5:$G$44) -> 245.25
A5: 2 · A cara e a energia | B5: Durante a fase 2 — precisa nas fases 3-5 | C5: =COUNTIF(Compras!$A$5:$A$44,A5) -> 12 | D5: =SUMIF(Compras!$A$5:$A$44,A5,Compras!$G$5:$G$44) -> 300
A6: 3 · Movimento e braços | B6: Durante a fase 4 — precisa nas fases 6-8 | C6: =COUNTIF(Compras!$A$5:$A$44,A6) -> 10 | D6: =SUMIF(Compras!$A$5:$A$44,A6,Compras!$G$5:$G$44) -> 142.8
A7: 4 · O corpo | B7: Durante a fase 8 — precisa na fase 13 | C7: =COUNTIF(Compras!$A$5:$A$44,A7) -> 7 | D7: =SUMIF(Compras!$A$5:$A$44,A7,Compras!$G$5:$G$44) -> 169
A8: 5 · Sobressalentes | B8: Com qualquer uma das outras | C8: =COUNTIF(Compras!$A$5:$A$44,A8) -> 1 | D8: =SUMIF(Compras!$A$5:$A$44,A8,Compras!$G$5:$G$44) -> 25
A9: TOTAL | D9: =SUM(D4:D8) -> 882.05
A11: Orçamento mínimo | D11: 400
A12: Orçamento máximo | D12: 1000
A13: Folga para upgrades | D13: =D12-D9 -> 117.95
A14: Dentro do orçamento? | D14: =IF(D9<=D12,"SIM","NÃO — rever") -> SIM
A17: ESTRATÉGIA DE COMPRA
A18: • REGRA: cada encomenda tem de CHEGAR antes da fase que precisa dela. A coluna Fase diz qual.
A19: • O reSpeaker é a placa de som do robô (microfones E coluna) e é preciso já na FASE 2 — por isso está na encomenda 1 e não na 4; o painel HUB75 na FASE 3. As encomendas agrupam-se pela fase em que a peça é precisa, não pelo tipo de peça.
A20: • Encomendar a seguinte enquanto se trabalha na fase anterior: os portes da Alemanha demoram uma semana.
A21: • Se o projeto parar na fase 5, pouparam-se ~€310 (as encomendas 3 e 4).
A22: • O Raspberry Pi é a peça cujo preço mais tem oscilado (escassez mundial de memória em 2026) — comprar cedo.
A23: • Comparar sempre Botnroll, Mauser e PTRobotics. No Pi 5 de 4 GB: Botnroll €95,90, PTRobotics €131,98, Mauser €119,88 e esgotado. Na câmara é ao contrário: Mauser €29,99, Botnroll €32,80.
A24: • Confirmar stock antes de encomendar — vários módulos apareciam esgotados durante a pesquisa.

Sheet Alternativas
A1: ALTERNATIVAS, UPGRADES E O QUE NÃO COMPRAR
A3: Item | B3: Preço | C3: Categoria | D3: Veredicto | E3: Porquê
A4: Ler os encoders com o ESP32 | C4: Upgrade da tração | D4: SIM — na v2 | E4: Os motores do mBot2 JÁ TÊM encoders e os fios já vão ligados ao Pi (GPIO 5, 6, 12, 13). O que falta é quem os conte: em Python no Pi 5, a ~1200 Hz por canal, desperdiça CPU — e o pigpio, que fazia isto por DMA, não funciona no Pi 5. O ESP32 que já temos tem 8 contadores de quadratura EM HARDWARE. Custo: zero.
A5: Modelo AMÁLIA 9B (LLM pt-PT) | C5: Upgrade do cérebro | D5: SIM — testar | E5: LLM aberto FEITO PARA PORTUGUÊS EUROPEU, de um consórcio nacional, licença Apache 2.0, treinado com o Arquivo.pt. Bate o Gemma 3-12B em exames em português. Mas não documenta tool calling — usar só para o 'modo conversa', não para dar ordens ao robô.
A6: Raspberry Pi 5 · 8 GB | B6: 189 | C6: Upgrade do cérebro | D6: NÃO | E6: +€93 para o mesmo resultado. O de 4 GB corre Whisper base + OpenCV sem problemas.
A7: Raspberry Pi 5 · 2 GB | B7: 68.9 | C7: Downgrade (poupança) | D7: PLANO B | E7: Poupa €27. Funciona, mas fica apertado com Whisper e OpenCV ao mesmo tempo. Só se o orçamento apertar.
A8: 2º sensor ToF VL53L1X — apontado ao chão | B8: 16.95 | C8: Fase 16 · seguir | D8: SIM, quando chegar a fase 16 | E8: ⚠️ O QUE TORNA O MODO SEGUIR SEGURO. Um TCRT5000 no para-choques vê o degrau ~5 cm à frente das rodas, o que só dá margem até ~27 cm/s — chega para a secretária, não chega para seguir alguém. Um ToF apontado obliquamente ao chão vê 30 cm à frente e sobe a velocidade segura para ~81 cm/s. ⚠️ Fica no mesmo endereço I2C (0x29) do que já temos: é preciso um pino XSHUT por sensor para os arrancar um de cada vez e mudar o endereço de um deles. Ver D17.
A9: AI HAT+ 26 TOPS (Hailo-8) | B9: 129.99 | C9: Acelerador de IA | D9: NÃO | E9: ⚠️ 15% do orçamento do robô para acelerar uma coisa que o CPU do Pi 5 já faz bem. Reconhecer 4-6 caras conhecidas corre a 15-25 FPS sem acelerador, e o robô precisa de 2-5. E NÃO faz IA generativa: não tem memória própria, é só visão — o YuNet e o SFace teriam de ser recompilados para o formato HEF da Hailo, ou seja refazer a perceção toda no SDK deles. €129,99 na Mauser (42 em stock).
A10: AI HAT+ 2 · 40 TOPS (Hailo-10H) — o do LLM local | B10: 220 | C10: Acelerador de IA | D10: NÃO (por agora) | E10: É o único que corre mesmo LLM e Whisper no próprio Pi: 8 GB de RAM próprios, 40 TOPS INT4, $130 nos EUA e £192 (~€220) na The Pi Hut. Três travões: (1) SÓ AGUENTA UM MODELO DE CADA VEZ — o Whisper tem de sair para o LLM entrar e vice-versa, que é exatamente a forma errada para um robô que conversa; (2) o Jeff Geerling mediu e o CPU do Pi 5 BATE-O a gerar tokens — 'a solution in search of a problem', e ele desistiu do exemplo de visão+LLM porque rebentava com segfault; (3) os modelos são de 1-1,5B (Llama3.2, Qwen2.5, DeepSeek-R1-Distill) contra os 12B do gemma4 no Mac, e ninguém documenta tool calling na stack da Hailo. Rever quando o robô quiser sair de casa sem o Mac.
A11: Coral USB Accelerator | C11: Acelerador de IA | D11: NÃO COMPRAR | E11: A Google ARQUIVOU o repositório google-coral/edgetpu em 19/04/2026. O PyCoral está preso ao Python 3.9 e não funciona no Raspberry Pi OS atual. Projeto morto. E mesmo vivo nunca serviria para voz: 8 MB de SRAM só dão para modelos de visão quantizados a int8.
A12: ReSpeaker 2-Mics Pi HAT | B12: 16 | C12: Áudio | D12: NÃO | E12: É a placa de todos os tutoriais de assistentes de voz — mas o repositório oficial do driver lista Pi 3, Pi 4 e Zero. O PI 5 NÃO APARECE. Há problemas conhecidos com kernels 6.x. Usar microfone USB.
A13: 2× OLED SSD1306 0,96" | B13: 17 | C13: A cara — alternativa | D13: ALTERNATIVA VÁLIDA | E13: I2C (2 fios), sem soldar, imune ao problema de GPIO do Pi 5. Mais fácil que o MAX7219 mas menos 'robô'. Precisa de endereços diferentes (0x3C/0x3D).
A14: Chassis tanque Keyestudio Mini Tank V3 | B14: 86.9 | C14: Chassis alternativo | D14: NÃO | E14: Boa mecânica com lagartas, mas traz um controlador Arduino que fica redundante com o Pi, e pede 2× 18650.
A15: Waveshare Motor Driver HAT | B15: 13.95 | C15: Driver alternativo | D15: REJEITADO NA v2 | E15: Era a escolha da v1. É I2C e funciona, mas o conector fêmea não tem passagem para cima — teria de se soldar um header empilhável ao próprio HAT. Com breakouts (2× PCA9685 + TB6612) numa protoboard, o GPIO fica todo acessível e cabe o pino OE.
A16: L298N | B16: 3.3 | C16: Driver alternativo | D16: NÃO | E16: Barato e omnipresente nos tutoriais, mas antiquado: perde ~2 V e aquece. Além disso depende de GPIO direto.
A17: HC-SR04 (versão normal 5 V) | B17: 3.6 | C17: Sensor | D17: NÃO COMPRAR | E17: ⚠️ Devolve 5 V no pino Echo e destrói o GPIO de 3,3 V do Pi. Poupa €1,30 e arrisca €95. Comprar a versão 'P'.
A18: Bateria LiPo/Li-ion 3S | B18: 30 | C18: Alimentação | D18: PLANO B | E18: ⚠️ Escolhemos LiFePO4 porque a química LFP não tem fuga térmica auto-alimentada. Se não houver stock de LiFePO4 (é escasso em PT), um pack 3S Li-ion COM BMS E EM CAIXA RÍGIDA é aceitável. Células nuas, nunca.
A19: Matriz MAX7219 32×16 azul | B19: 9.8 | C19: A cara — alternativa | D19: REJEITADA na v3 | E19: Era a escolha até existir o bot-face. Barata, madura e sem risco — mas monocromática. O Astro mostra corações vermelhos, e o demo já tinha a expressão 'heart'. 512 px contra 2048.
A20: 2× ecrã redondo GC9A01 240×240 | B20: 31.2 | C20: A cara — alternativa | D20: NÃO | E20: ⚠️ Cai por causa do faceplate escuro: um LCD de 280 nits atrás de acrílico a 18% fica em ~50 nits, ilegível numa sala iluminada. A luz emitida atravessa o acrílico 1x, os reflexos 2x — o acrílico escuro favorece fontes emissivas e penaliza LCDs. E perde-se o aspeto pixelado, que é o que queremos.
A21: HUB75 ligado diretamente ao Raspberry Pi 5 | C21: A cara — alternativa | D21: NÃO | E21: ⚠️ A PioMatter funciona mas exige 13 pinos GPIO, e QUATRO colidem com o que já temos: 17, 22 e 27 (sensores de precipício) e 23 (ultrassons). Além disso não tem versão nova há 13 meses e gastaria um core do Pi. O ESP32 resolve tudo isto por 0 euros.
A22: Regulador de 5 A para os servos | B22: 35 | C22: Alimentação | D22: NÃO CHEGA | E22: ⚠️ Os stalls somados dão ~8,4 A (2× DS3218 a ~3 A + 3× MG90S a ~0,7 A). Um regulador de 5 A com 2200 µF só cobre ~1 ms de défice. Comprar 6 A, e escalonar o arranque dos servos no software.
A23: Botão de emergência de 1 polo | B23: 8 | C23: Segurança | D23: NÃO | E23: ⚠️ Com um polo só, os barramentos de 5,7 V e 7,4 V ficariam ligados um ao outro através do botão. Tem de ser DPST.
A24: Câmara OV5647 5 MP c/ foco ajustável e 2 iluminadores IR | B24: 21.9 | C24: Câmara — alternativa | D24: NÃO (mas SIM como extra, depois) | E24: ⚠️ Mais barata (-€11) e faz visão noturna — mas para RECONHECER CARAS é pior em três pontos. (1) Para os IR servirem, o sensor não tem filtro de infravermelhos: de dia o IR do sol e das lâmpadas entra como se fosse vermelho e a pele fica cerosa e sem cor. (2) O SFace foi treinado com fotografias de luz visível; a assinatura de uma cara iluminada a IR cai noutra distribuição (o problema NIR-VIS da literatura) — a Lara registava-se de dia e à noite deixava de ser reconhecida. (3) Foco manual por parafuso: fixa-se uma vez. NOTA: o Pi 5 tem DUAS entradas CSI. Isto pode entrar mais tarde como segunda câmara de 'modo noturno', sem tirar nada.
A25: InnoMaker 4K 8 MP STARVIS IMX415 (Amazon.es B0G633SLR1) | B25: 31 | C25: Câmara — alternativa | D25: PLANO B | E25: A melhor das três alternativas vistas na Amazon, e a única que ENTREGA EM PORTUGAL. Sensor Sony STARVIS retroiluminado, 0,01 lux, com filtro de IR (não é NoIR). Traz os DOIS cabos, 15 e 22 pinos — dispensa o adaptador de €4,50, por isso fica €31 contra €37,30. MAS: foco manual por parafuso, não tem autofoco. E precisa de dtoverlay=imx415 no config.txt (o libcamera suporta-o desde 0.5.0+rpi20250707, kernel 6.12.25+). Usar só se a Camera Module 3 faltar no Botnroll.
A26: InnoMaker IMX708 autofoco (Amazon.es B0DJ6R67CY) | B26: 48.36 | C26: Câmara — alternativa | D26: NÃO | E26: ⚠️ Mesmo sensor da Camera Module 3 e autofoco PDAF — mas €48,36, ou seja €15 MAIS CARO que o módulo oficial. Vem dos EUA e NÃO ENTREGA EM PORTUGAL. 3,8 estrelas com 29% de avaliações de 1-2 estrelas, várias mortas à chegada em Espanha e França. Exige camera_auto_detect=0 + dtoverlay=imx708.
A27: Arducam Camera Module 3 B0312 (Amazon.es B0C9PYCV9S) | B27: 33.52 | C27: Câmara — alternativa | D27: NÃO | E27: ⚠️ Parece o módulo oficial e não é: a própria página diz 'different from official V3 camera, this camera needs some modification in configuration before use'. Traz o cabo 15→22, o que seria bom, mas vem do Reino Unido e NÃO ENTREGA EM PORTUGAL. €33,52 pelo não-oficial contra €32,80 pelo oficial no Botnroll não faz sentido.
A28: Camera Module 1 / OV5647 em geral (qualquer clone) | C28: Câmara — alternativa | D28: CUIDADO | E28: A Camera Module 1 foi DESCONTINUADA pela Raspberry Pi. O driver continua no kernel e funciona, mas os clones nem sempre são apanhados pelo camera_auto_detect=1 e obrigam a pôr dtoverlay=ov5647 à mão no config.txt — há tópicos recorrentes no fórum oficial sobre exatamente isto no Pi 5. Se for versão NoIR ainda é preciso passar o ficheiro de tuning ov5647_noir.json ao libcamera. IMPORTANTE: o cabo adaptador 22→15 é preciso na mesma — não é uma desvantagem desta câmara, é do Pi 5.
A29: Módulo M.2 HAT+ (SSD NVMe) | B29: 12.95 | C29: Armazenamento | D29: NÃO | E29: Mais rápido, mas um cartão microSD A2 chega para um robô, consome menos e é mais fácil de substituir quando a Lara o corromper (vai acontecer).
A30: Amplificador I2S MAX98357A ligado ao Pi | B30: 8 | C30: Som — alternativa | D30: REJEITADO na v4.2 | E30: ⚠️ Era a escolha até 25/08/2026 e estava errada. Em modo USB, o XVF3800 só cancela o eco se for o Pi a mandar-lhe o áudio por USB — é esse fluxo que serve de referência ('the USB host provides the reference signal', documentação XMOS). Um amplificador no I2S do Pi toca ao lado do reSpeaker, que fica sem referência: os €60 de AEC deixavam de servir. A coluna liga-se à ficha JST PH 2.0 da placa do reSpeaker (saída amplificada, até 5 W). Bónus: zero soldadura na fase 2, nada no config.txt, GPIO 18/19/21 livres.

Sheet Lojas
A1: ONDE COMPRAR
A3: Loja | B3: País | C3: Site | D3: Notas
A4: Botnroll | B4: Portugal | C4: botnroll.com | D4: MELHOR PREÇO no Raspberry Pi 5 (€95,90 os 4 GB) e catálogo forte de sensores. Primeira paragem. Tem a coluna certa ('Coluna stereo - 3W', €4,95) — mas NÃO tem o reSpeaker nem amplificadores I2S.
A5: Mauser | B5: Portugal | C5: mauser.pt | D5: SEGUNDA PARAGEM, e a melhor para a câmara: Camera Module 3 oficial a €29,99 (80 em stock) e cabo oficial SC1892 a €1,17 (224 em stock). SETE LOJAS FÍSICAS com levantamento GRÁTIS — Porto, Lisboa, Leiria, Corroios, Portela, Freixeira, Funchal. Portes €3,49 abaixo de €50, grátis acima. ⚠️ NÃO comprar aqui o Pi 5: €119,88 e sem stock.
A6: PTRobotics | B6: Portugal | C6: ptrobotics.com | D6: Bom catálogo e envio rápido, mas caro no Pi (€131,98 os mesmos 4 GB). Útil para peças que a Botnroll não tenha.
A7: BerryBase | B7: Alemanha | C7: berrybase.de | D7: Muito bom em módulos pequenos e breakouts baratos. Contar com portes e prazo maior.
A8: Welectron | B8: Alemanha | C8: welectron.com | D8: Alternativa alemã, boa para HATs e câmaras. Verificar se a listagem está ativa — tem entradas duplicadas.
A9: The Pi Hut | B9: Reino Unido | C9: thepihut.com | D9: Referência para módulos Adafruit/Pimoroni e para o reSpeaker. ⚠️ Pós-Brexit: pode haver taxas alfandegárias.
A10: Pimoroni | B10: Reino Unido | C10: shop.pimoroni.com | D10: HATs de qualidade e bem documentados. Mesmo aviso alfandegário.
A11: Gotronic | B11: França | C11: gotronic.fr | D11: reSpeaker XVF3800 a €59,90 com IVA, dentro da UE (sem alfândega). Esgota com frequência — a página mostra a data de reposição (a 25/08/2026 dizia 28/08).
A12: Kiwi Electronics | B12: Holanda | C12: kiwi-electronics.com | D12: reSpeaker XVF3800 a €48,99 + IVA quando há stock (esgotada a 25/08/2026). Dentro da UE.
A13: ANTES DE ENCOMENDAR — checklist
A14: ☐ Confirmar que o preço do Raspberry Pi não mudou (tem oscilado muito em 2026)
A15: ☐ Confirmar STOCK de cada item — vários apareciam esgotados durante a pesquisa
A16: ☐ Confirmar que o sensor ultrassónico é o modelo HC-SR04P (3,3 V) e não o normal
A17: ☐ Confirmar que o cabo CSI adaptador 22→15 pinos está no carrinho
A18: ☐ Somar os portes: às vezes compensa juntar tudo numa loja mais cara
A19: ☐ Ver se o módulo vem com os headers já soldados (poupa trabalho e risco)
A20: ☐ Confirmar que o reSpeaker XVF3800 está no carrinho da encomenda 1 — é a placa de som, não só os ouvidos

Sheet Impressora 3D
A1: IMPRESSORA 3D — INVESTIMENTO FUTURO
A2: NÃO entra no total do robô. Não é preciso para começar: o corpo faz-se em cartão até à fase 13.
A4: Item | B4: Preço | C4: Fechada? | D4: Volume | E4: Veredicto | F4: Porquê
A5: Bambu Lab P1S | B5: 379 | C5: Sim | D5: 256 mm | E5: RECOMENDADA | F5: Fechada (barreira física contra um bico a 250C, com uma criança por perto), filtro de carvão ativado, e 256mm chega para a cúpula da cabeça em 2 metades. Ecossistema mais fácil do mercado para quem começa.
A6: Filamento inicial (PLA branco + azul + PETG) | B6: 45 | C6: — | D6: — | E6: COMPRAR COM | F6: As cores do Astro. O PETG é para as peças que tocam no Pi e nos reguladores — o PLA amolece aos 60C.
A7: Bambu Lab A1 | B7: 259 | C7: NÃO | D7: 256 mm | E7: ALTERNATIVA | F7: Excelente máquina e 120 euros mais barata, mas ABERTA. Com uma criança de 11 anos, esses 120 euros compram uma barreira à volta do bico quente e da mesa que se move.
A8: Bambu Lab A1 mini | B8: 189 | C8: NÃO | D8: 180 mm | E8: EVITAR | F8: ⚠️ 180mm obriga a partir a cúpula da cabeça em 4-6 gomos, com muitas juntas a lixar e colar. Frustração garantida para uma criança.
A9: Elegoo Centauri Carbon 2 Combo | B9: 379 | C9: Sim | D9: 256 mm | E9: ALTERNATIVA FORTE | F9: Fechada E já com multicor, pelo mesmo preço da P1S. A melhor relação preço/valor de 2026, se não fizerem questão do ecossistema Bambu.
A10: Bambu Lab P2S | B10: 519 | C10: Sim | D10: 256 mm | E10: NÃO COMPENSA | F10: A P1S melhorada (out/2025): extrusor DynaSense, deteção de erros por IA. Melhor, mas não 140 euros melhor para este uso.
A11: Prusa MK4S | B11: 719 | C11: Não | D11: 250x210x220 | E11: FORA DO ÂMBITO | F11: Fabricante europeu, open-source, peças e apoio na UE. Ótima máquina, mas o dobro do que este projeto precisa.
A12: AMS lite — impressão multicor | B12: 110 | C12: — | D12: — | E12: NÃO | F12: ⚠️ Parece óbvio para um robô branco e azul, mas não é: desperdiça ~8g de filamento POR TROCA DE COR (81% do filamento numa peça pequena com 8 trocas). As nossas peças são grandes e de UMA cor — troca-se o rolo à mão entre peças, 2 minutos. Só compensaria para várias cores DENTRO da mesma peça.
A13: Purificador de ar HEPA + carvão | B13: 115 | C13: — | D13: — | E13: SE FOR EM CASA | F13: ⚠️ Só se a impressora ficar numa divisão habitada. O filtro de carvão da P1S trata dos COVs mas NÃO É HEPA — não apanha as partículas ultrafinas. Melhor ainda: pôr a impressora na garagem ou num escritório com janela.
A15: PARA ARRANCAR (P1S + filamento) | B15: =B5+B6 -> 424
A17: SEGURANÇA — as cinco regras
A18: Um relatório da UL Chemical Insights, feito em salas de aula, mediu mais de 200 COVs distintos em impressoras FDM, formaldeído acima do dobro do limite recomendado da Califórnia, e 3,4x10^8 partículas ultrafinas por hora mesmo com PLA. O relatório avisa explicitamente para crianças. Ou seja: o PLA é o mais seguro, mas não é seguro sem cuidados.
A19: 1. Impressora FECHADA — barreira física contra queimaduras, contém a maior parte das partículas, e reduz muito o ruído.
A20: 2. NÃO no quarto dela. Garagem, arrumos, ou escritório com janela.
A21: 3. Só PLA e PETG. Nada de ABS ou ASA em casa sem extração para o exterior.
A22: 4. A criança carrega o ficheiro e vê pela câmara; só abre a tampa depois de arrefecer.
A23: 5. O filtro de carvão trata dos COVs mas NÃO É HEPA — não apanha partículas ultrafinas. Daí a regra 2.
A25: CUSTO CONTINUADO
A26: O robô inteiro consome 1,5-2,5 kg de filamento = 25-40 euros.
A27: Eletricidade: cerca de 2 cêntimos por hora. Desprezável — o filamento custa 5 a 50x mais.
A28: Desgaste (bicos 10-15 euros, placa 25-40, correias): orçamentar 40-60 euros por ano.
A29: ⚠️ Uma metade de cúpula demora 8 a 20 HORAS a imprimir. Uma cabeça completa é um fim de semana. Dizer isto à Lara no primeiro dia — a expectativa errada aqui estraga a experiência toda.
A30: ANTES DE COMPRAR: o FabLab Porto (Rua António Carneiro 302-R, seg-sex 14h-20h) e o FabLab Lisboa deixam ver máquinas a trabalhar. Meia hora bem passada antes de gastar 400 euros.

Sheet A bancada
A1: A BANCADA — FERRAMENTAS
A2: Ferramentas duram uma vida e servem para tudo o resto. Por isso estão FORA do total do robô, como a impressora 3D.
A4: Item | B4: Preço | C4: Essencial? | D4: Porquê / o que escolher
A5: Estação de soldar com base pesada (936 / Yihua) | B5: 30 | C5: SIM | D5: ⚠️ COM UMA CRIANÇA POR PERTO, O SUPORTE PESADO IMPORTA MAIS QUE O FERRO. Uma estação de 30 euros com base estável é mais segura que um ferro portátil pousado na mesa. Ponto de retorno decrescente: ~40 euros. Um Hakko de 120 ou um JBC de 400 não ensinam melhor.
A6: Solda SEM CHUMBO 0,7 mm, 100 g | B6: 14 | C6: SIM | D6: ⚠️ RECOMENDO SEM CHUMBO, e não a 60/40 clássica. Funde a 217C em vez de 183C e molha um pouco pior, mas apaga uma preocupação inteira numa casa com crianças. O manual de segurança da FIRST Robotics exige mesmo 'lead-free solder only'. Diâmetro 0,7 mm: 1 mm é grosso demais para pinos.
A7: Fluxo em caneta, no-clean | B7: 8 | C7: SIM | D7: Com solda sem chumbo o fluxo extra deixa de ser luxo. Uma caneta dura anos.
A8: Lã de latão para limpar a ponta | B8: 6 | C8: SIM | D8: Melhor que a esponja molhada: não arrefece a ponta de repente, o que a faz durar muito mais.
A9: Ponta chisel 2,4 mm de reserva | B9: 5 | C9: SIM | D9: ⚠️ A ponta CHISEL é a certa para principiante — transfere muito mais calor que a de agulha, que é a pior escolha e a que toda a gente experimenta primeiro.
A10: Malha dessoldadora + bomba | B10: 10 | C10: SIM | D10: Para desfazer erros. Vão precisar nas primeiras vinte juntas.
A11: Terceira mão (helping hands) | B11: 8 | C11: SIM | D11: Duas mãos seguram o ferro e a solda; não sobra nenhuma para a placa.
A12: Alicate de corte flush + descarnador | B12: 18 | C12: SIM | D12: O descarnador é usado em todas as fases, mesmo sem soldar.
A13: Óculos de proteção (2 pares) | B13: 8 | C13: SIM | D13: ⚠️ O risco ocular real NÃO é o fumo — é o terminal cortado a saltar. Dois pares: um para cada um.
A14: Kit de prática (Whadda WSI102 ou similar) | B14: 15 | C14: SIM | D14: ⚠️ FAZER ~100 JUNTAS ANTES DE TOCAR NO PI DE 95 EUROS. 15 euros contra o risco de destruir 95: não há discussão. E é o sítio certo para a Lara experimentar — uma placa de treino não tem nada a perder.
A15: Multímetro (se não tiverem) | B15: 25 | C15: SIM | D15: Ferramenta central da fase 4 (descobrir a pinagem dos motores do mBot2) e da 5 (ajustar os reguladores). Precisa de continuidade e tensão DC.
A16: Ventoinha USB pequena | B16: 12 | C16: RECOMENDADO | D16: Posta a PUXAR o ar para longe das caras. A seguir a 'não se debruçar sobre a junta', é o maior ganho de segurança por euro. Uma janela aberta e esta ventoinha valem mais que um extrator caro mal colocado.
A17: Extrator de fumos com filtro de carvão | B17: 30 | C17: OPCIONAL | D17: Só funciona a 10-15 cm da junta. A HSE avisa que estas unidades 'do not capture all of the fume particles'. Janela + ventoinha primeiro; isto se soldarem muito.
A18: Estação de ar quente / microscópio / pasta de solda | C18: NAO COMPRAR | D18: ⚠️ Nada disto é preciso para este projeto. São a tentação clássica de quem começa.
A20: TOTAL DA BANCADA (só os essenciais) | B20: =SUMIF(C5:C18,"SIM",B5:B18) -> 147
A22: SEGURANÇA — os factos, sem alarmismo
A23: O CHUMBO NÃO EVAPORA. Funde a 327C e ferve a 1749C; soldamos a 350C. A via de exposição real é MAO-BOCA, não o ar (Columbia University EHS: 'the primary route of exposure to lead from soldering is ingestion'). LAVAR AS MAOS COM SABAO a seguir resolve quase tudo. Mesmo assim, recomendo solda sem chumbo: apaga a questão inteira.
A25: O FUMO QUE SE VE E O FLUXO, NAO O METAL — e ESSE é o risco a sério. A HSE britânica classifica o fumo de colofónia como 'a common cause of occupational asthma', e a sensibilização é PERMANENTE: uma vez sensibilizado, doses mínimas desencadeiam crise.
A27: AS TRES MEDIDAS, POR ORDEM DE EFICACIA POR EURO:
A28: 1. NAO SE DEBRUCAR SOBRE A JUNTA. Custa zero e é o maior ganho isolado.
A29: 2. Janela aberta + ventoinha a PUXAR o ar para longe das caras (~12 euros).
A30: 3. Extrator com filtro de carvão, e só serve a 10-15 cm da junta (~30 euros).
A32: REGRAS DE CASA: ferro sempre no suporte · cabo longe da borda · cabelo apanhado e sem mangas largas · OCULOS DE PROTECAO (o risco é o terminal cortado a saltar, não o fumo) · nada de comer nem beber na bancada · lavar as mãos a seguir · limpar a bancada com pano HUMIDO, nunca varrer · nunca deixar o ferro ligado sem vigilância · queimadura: água fria corrente 20 minutos.
A34: QUANDO É QUE A LARA PODE SOLDAR? O manual de segurança da FIRST Robotics normaliza 10-13 anos com supervisão 1:1, e o FTC aceita a partir dos 12. O critério prático é melhor que a idade: ELA PODE SOLDAR QUANDO PUSER O FERRO NO SUPORTE DE FORMA FIAVEL ENTRE JUNTAS, sem ter de se lembrar. Testar isso no kit de prática, que não tem nada a perder.
A36: QUANTA SOLDADURA ESTE PROJETO PRECISA MESMO
A37: Com as escolhas certas na lista de compras, quase nenhuma:
A38: JA VEM SOLDADO: reSpeaker XVF3800 (USB; a coluna encaixa numa ficha JST PH 2.0 — substituiu o amplificador I2S MAX98357A, que obrigava a soldar 5 fios) · PCA9685 (clones — o da Adafruit exigiria 48 juntas!) · TB6612FNG (versão SparkFun 'with Headers') · ADS1115 · HC-SR04P · VL53L1X · TCRT5000
... A44: OPINIAO HONESTA: aprendam a soldar. São umas 4 horas de prática e elimina a causa número um de robôs de hobby que 'às vezes funcionam' — contactos intermitentes. Mas usem as soluções sem soldar no caminho de POTENCIA, porque é aí que uma junta má deixa de ser uma chatice e passa a ser um perigo.
